gobble/__init__.py
gobble/gobble.py
gobble/assets/gobble000.png
gobble/assets/gobble001.png
gobble/assets/gobble002.png
gobble/assets/gobble003.png
gobble/assets/gobble004.png
gobble/assets/gobble005.png
gobble/assets/gobble006.png
gobble/assets/gobble007.png
gobble/assets/gobble008.png
gobble/assets/gobble009.png
gobble/assets/gobble010.png
gobble/assets/gobble011.png
gobble/assets/gobble012.png
gobble/assets/gobble013.png
gobble/assets/gobble014.png
gobble/assets/gobble015.png
gobble/assets/gobble016.png
gobble/assets/gobble017.png
gobble/assets/gobble018.png
gobble/assets/gobble019.png
gobble/assets/gobble020.png
gobble/assets/gobble021.png
gobble/assets/gobble022.png
gobble/assets/gobble023.png
gobble/assets/gobble024.png
gobble/assets/gobble025.png
gobble/assets/gobble026.png
gobble/assets/gobble027.png
gobble/assets/gobble028.png
gobble/assets/gobble029.png
gobble/assets/gobble030.png
gobble/assets/gobble031.png
gobble/assets/gobble032.png
gobble/assets/gobble033.png
gobble/assets/gobble034.png
gobble/assets/gobble035.png
gobble/assets/gobble036.png
gobble/assets/gobble037.png
gobble/assets/gobble038.png
gobble/assets/gobble039.png
gobble/assets/gobble040.png
gobble/assets/gobble041.png
gobble/assets/gobble042.png
gobble/assets/gobble043.png
gobble/assets/gobble044.png
gobble/assets/gobble045.png
gobble/assets/gobble046.png
gobble/assets/gobble047.png
gobble/assets/gobble048.png
gobble/assets/gobble049.png
gobble/assets/gobble050.png
gobble/assets/gobble051.png
gobble/assets/gobble052.png
gobble/assets/gobble053.png
gobble/assets/gobble054.png
gobble/assets/gobble055.png
gobble/assets/gobble056.png
gobble/assets/gobble057.png
gobble/assets/gobble058.png
gobble/assets/gobble059.png
gobble/assets/gobble060.png
gobble/assets/gobble061.png
gobble/assets/gobble062.png
gobble/assets/gobble063.png
gobble/assets/gobble064.png
gobble/assets/gobble065.png
gobble/assets/gobble066.png
gobble/assets/gobble067.png
gobble/assets/gobble068.png
gobble/assets/gobble069.png
gobbler-0.2.2.dist-info/METADATA
gobbler-0.2.2.dist-info/WHEEL
gobbler-0.2.2.dist-info/entry_points.txt
gobbler-0.2.2.dist-info/top_level.txt
gobbler-0.2.2.dist-info/RECORD
