Metadata-Version: 2.1
Name: gobbler
Version: 0.2.2
Summary: Turkey-themed image catalog to boost the holiday mood.
Home-page: https://github.com/rayssharma/gobble
Author: Ray Sharma
Author-email: ramon.sharma1@gmail.com
License: MIT
Download-URL: https://github.com/rayssharma/gobble/tarball/0.2.2
Platform: UNKNOWN
Classifier: Development Status :: 4 - Beta
Classifier: License :: OSI Approved :: MIT License
Classifier: Topic :: Office/Business :: Financial
Classifier: Topic :: Scientific/Engineering :: Mathematics
Classifier: Topic :: Software Development :: Libraries :: Python Modules
Classifier: Programming Language :: Python :: 3
Classifier: Programming Language :: Python :: 3.5
Classifier: Programming Language :: Python :: 3.6
Classifier: Programming Language :: Python :: 3.7
Requires-Dist: pillow (>=6.2.1)
Requires-Dist: pytest
